<annotation>
	<folder>WH_data</folder>
	<filename>oiltank_114.jpg</filename>
	<source>
		<database>WH Data</database>
		<annotation>WH</annotation>
		<image>flickr</image>
		<flickrid>NULL</flickrid>
	</source>
	<owner>
		<flickrid>NULL</flickrid>
		<name>WH</name>
	</owner>
	<size>
		<width>1083</width>
		<height>923</height>
		<depth>3</depth>
	</size>
		<segmented>0</segmented>
	<object>
		<name>oiltank</name>
		<pose>Unspecified</pose>
		<truncated>1</truncated>
		<difficult>0</difficult>
		<bndbox>
			<xmin>359</xmin>
			<ymin>295</ymin>
			<xmax>492</xmax>
			<ymax>416</ymax>
		</bndbox>
	</object>
	<object>
		<name>oiltank</name>
		<pose>Unspecified</pose>
		<truncated>1</truncated>
		<difficult>0</difficult>
		<bndbox>
			<xmin>305</xmin>
			<ymin>442</ymin>
			<xmax>444</xmax>
			<ymax>577</ymax>
		</bndbox>
	</object>
	<object>
		<name>oiltank</name>
		<pose>Unspecified</pose>
		<truncated>1</truncated>
		<difficult>0</difficult>
		<bndbox>
			<xmin>465</xmin>
			<ymin>482</ymin>
			<xmax>597</xmax>
			<ymax>614</ymax>
		</bndbox>
	</object>
	<object>
		<name>oiltank</name>
		<pose>Unspecified</pose>
		<truncated>1</truncated>
		<difficult>0</difficult>
		<bndbox>
			<xmin>508</xmin>
			<ymin>335</ymin>
			<xmax>642</xmax>
			<ymax>458</ymax>
		</bndbox>
	</object>
</annotation>